odoo/addons/edi_exchange_template_party_data/README.rst
odoo/addons/edi_exchange_template_party_data/__init__.py
odoo/addons/edi_exchange_template_party_data/__manifest__.py
odoo/addons/edi_exchange_template_party_data/i18n/edi_exchange_template_party_data.pot
odoo/addons/edi_exchange_template_party_data/i18n/es.po
odoo/addons/edi_exchange_template_party_data/i18n/it.po
odoo/addons/edi_exchange_template_party_data/models/__init__.py
odoo/addons/edi_exchange_template_party_data/models/edi_exchange_template_output.py
odoo/addons/edi_exchange_template_party_data/readme/CONTRIBUTORS.md
odoo/addons/edi_exchange_template_party_data/readme/DESCRIPTION.md
odoo/addons/edi_exchange_template_party_data/static/description/icon.png
odoo/addons/edi_exchange_template_party_data/static/description/index.html
odoo/addons/edi_exchange_template_party_data/tests/__init__.py
odoo/addons/edi_exchange_template_party_data/tests/test_output_tmpl.py
odoo_addon_edi_exchange_template_party_data-18.0.1.0.1.2.dist-info/METADATA
odoo_addon_edi_exchange_template_party_data-18.0.1.0.1.2.dist-info/WHEEL
odoo_addon_edi_exchange_template_party_data-18.0.1.0.1.2.dist-info/top_level.txt
odoo_addon_edi_exchange_template_party_data-18.0.1.0.1.2.dist-info/RECORD
