Metadata-Version: 2.1
Name: odoo-addon-edi_exchange_template_party_data
Version: 18.0.1.0.1.2
Requires-Python: >=3.10
Requires-Dist: odoo-addon-edi_exchange_template_oca==18.0.*
Requires-Dist: odoo-addon-edi_party_data_oca==18.0.*
Requires-Dist: odoo==18.0.*
Summary: Glue module between edi_exchange_template and edi_party_data
Home-page: https://github.com/OCA/edi-framework
License: AGPL-3
Author: Camptocamp,Odoo Community Association (OCA)
Author-email: support@odoo-community.org
Classifier: Programming Language :: Python
Classifier: Framework :: Odoo
Classifier: Framework :: Odoo :: 18.0
Classifier: License :: OSI Approved :: GNU Affero General Public License v3
Classifier: Development Status :: 3 - Alpha
